testmailhelper/__init__.py
testmailhelper/client.py
TestMailHelper-0.3.2.dist-info/LICENSE
TestMailHelper-0.3.2.dist-info/METADATA
TestMailHelper-0.3.2.dist-info/WHEEL
TestMailHelper-0.3.2.dist-info/top_level.txt
TestMailHelper-0.3.2.dist-info/RECORD
