Metadata-Version: 2.1
Name: TestMailHelper
Version: 0.3.2
Summary: A Python package for interacting with the Testmail.app API.
Home-page: https://github.com/tensor35/TestMailHelper
Author: Muhammad Ali
Author-email: muhammad_ali@workmail.com
Classifier: Programming Language :: Python :: 3
Classifier: License :: OSI Approved :: MIT License
Classifier: Operating System :: OS Independent
Requires-Python: >=3.6
License-File: LICENSE
Requires-Dist: requests
